toponym/__init__.py
toponym/case.py
toponym/main.py
toponym/recipes.py
toponym/settings.py
toponym/topodict.py
toponym/toponym.py
toponym/utils.py
toponym/resources/_test.json
toponym/resources/el.json
toponym/resources/hr.json
toponym/resources/hu.json
toponym/resources/lv.json
toponym/resources/pl.json
toponym/resources/ro.json
toponym/resources/ru.json
toponym/resources/uk.json
toponym-0.5.1.dist-info/entry_points.txt
toponym-0.5.1.dist-info/LICENSE
toponym-0.5.1.dist-info/WHEEL
toponym-0.5.1.dist-info/METADATA
toponym-0.5.1.dist-info/RECORD
