Metadata-Version: 2.1
Name: toponym
Version: 0.5.1
Summary: Extract and count countries and cities (+their synonyms) from text
Home-page: https://github.com/iwpnd/toponym
License: UNKNOWN
Author: Benjamin Ramser
Author-email: ahoi@iwpnd.pw
Requires-Python: >=3.6
Classifier: Operating System :: OS Independent
Classifier: Programming Language :: Python :: 3
Classifier: Programming Language :: Python
Classifier: Topic :: Software Development :: Libraries :: Python Modules
Classifier: Topic :: Software Development :: Libraries
Classifier: Typing :: Typed
Classifier: Intended Audience :: Developers
Classifier: License :: OSI Approved :: MIT License
Classifier: Programming Language :: Python :: 3 :: Only
Classifier: Programming Language :: Python :: 3.6
Classifier: Programming Language :: Python :: 3.7
Classifier: Programming Language :: Python :: 3.8
Requires-Dist: loguru==0.4.1
Requires-Dist: pydantic==1.4
Requires-Dist: typer==0.2.1
Requires-Dist: safer==2.0.5
Requires-Dist: awscli ; extra == "doc"
Requires-Dist: mkdocs==1.0.4 ; extra == "doc"
Requires-Dist: mkdocs-material==4.6.3 ; extra == "doc"
Requires-Dist: markdown-include ; extra == "doc"
Requires-Dist: pydoc-markdown==2.0.5 ; extra == "doc"
Requires-Dist: pytest >=4.0.0 ; extra == "test"
Requires-Dist: pytest-cov ; extra == "test"
Project-URL: Documentation, https://toponym.iwpnd.pw/
Provides-Extra: all
Provides-Extra: dev
Provides-Extra: doc
Provides-Extra: test
